or_lib/__init__.py
or_lib/algorithms.py
or_lib/base.py
or_lib/exceptions.py
or_lib/lightrag.py
or_lib/llm.py
or_lib/namespace.py
or_lib/operate.py
or_lib/prompt.py
or_lib/types.py
or_lib/utils.py
or_lib/api/__init__.py
or_lib/api/auth.py
or_lib/api/gunicorn_config.py
or_lib/api/lightrag_server.py
or_lib/api/run_with_gunicorn.py
or_lib/api/utils_api.py
or_lib/api/routers/__init__.py
or_lib/api/routers/document_routes.py
or_lib/api/routers/graph_routes.py
or_lib/api/routers/ollama_api.py
or_lib/api/routers/query_routes.py
or_lib/kg/__init__.py
or_lib/kg/age_impl.py
or_lib/kg/chroma_impl.py
or_lib/kg/faiss_impl.py
or_lib/kg/gremlin_impl.py
or_lib/kg/json_doc_status_impl.py
or_lib/kg/json_kv_impl.py
or_lib/kg/milvus_impl.py
or_lib/kg/mongo_impl.py
or_lib/kg/nano_vector_db_impl.py
or_lib/kg/neo4j_impl.py
or_lib/kg/networkx_impl.py
or_lib/kg/oracle_impl.py
or_lib/kg/postgres_impl.py
or_lib/kg/qdrant_impl.py
or_lib/kg/redis_impl.py
or_lib/kg/shared_storage.py
or_lib/kg/tidb_impl.py
or_lib/llm/__init__.py
or_lib/llm/azure_openai.py
or_lib/llm/bedrock.py
or_lib/llm/hf.py
or_lib/llm/jina.py
or_lib/llm/llama_index_impl.py
or_lib/llm/lmdeploy.py
or_lib/llm/lollms.py
or_lib/llm/nvidia_openai.py
or_lib/llm/ollama.py
or_lib/llm/openai.py
or_lib/llm/siliconcloud.py
or_lib/llm/zhipu.py
or_lib/tools/__init__.py
or_lib/tools/lightrag_visualizer/__init__.py
or_lib/tools/lightrag_visualizer/graph_visualizer.py
or_lib-1.3.0.dist-info/licenses/LICENSE
or_lib-1.3.0.dist-info/METADATA
or_lib-1.3.0.dist-info/WHEEL
or_lib-1.3.0.dist-info/entry_points.txt
or_lib-1.3.0.dist-info/top_level.txt
or_lib-1.3.0.dist-info/RECORD
