Metadata-Version: 2.4
Name: or_lib
Version: 1.3.0
Summary:    OptimisedRAG: Simple and Fast Retrieval-Augmented Generation a modified version of LightRAG
Home-page: https://github.com/MdNazishArman2803
Author: MdNazishArman
Project-URL: Documentation, https://github.com/MdNazishArman2803
Project-URL: Source, https://github.com/MdNazishArman2803
Project-URL: Tracker, https://github.com/MdNazishArman2803/issues
Classifier: Development Status :: 4 - Beta
Classifier: Programming Language :: Python :: 3
Classifier: License :: OSI Approved :: MIT License
Classifier: Operating System :: OS Independent
Classifier: Intended Audience :: Developers
Classifier: Topic :: Software Development :: Libraries :: Python Modules
Requires-Python: >=3.9
License-File: LICENSE
Provides-Extra: api
Provides-Extra: tools
Dynamic: author
Dynamic: classifier
Dynamic: description
Dynamic: description-content-type
Dynamic: home-page
Dynamic: license-file
Dynamic: project-url
Dynamic: provides-extra
Dynamic: requires-python
Dynamic: summary
